LICENSE.txt
README.md
setup.py
asiacell/__init__.py
asiacell/asiacell.py
asiacell.py.egg-info/PKG-INFO
asiacell.py.egg-info/SOURCES.txt
asiacell.py.egg-info/dependency_links.txt
asiacell.py.egg-info/requires.txt
asiacell.py.egg-info/top_level.txt
asiacell/utils/__init__.py
asiacell/utils/client.py
asiacell/utils/exceptions.py
asiacell/utils/headers.py
asiacell/utils/helpers.py
asiacell/utils/models.py
asiacell/utils/response.py