Metadata-Version: 2.1
Name: asiacell.py
Version: 1.0.0
Summary: Unofficial Python wrapper for Asiacell API.
Home-page: https://github.com/ahmadelbd/Asiacell
Download-URL: https://github.com/ahmadelbd/Asiacell/archive/refs/heads/main.zip
Author: LSFR | ahmadelbd
Author-email: mustafadev.py@gmail.com
License: MIT
Keywords: asiacell,asiacell.pyasia,asiacell-api,ahmadelbd,lsfr,asiacell-wrapper,asiacell-bot
License-File: LICENSE.txt
